<annotation verified="no">
	<folder>louis vuitton</folder>
	<filename>82_LOUIS-VUITTON.jpg</filename>
	<source>
		<database>Unknown</database>
	</source>
	<size>
		<width>397</width>
		<height>517</height>
		<depth>3</depth>
	</size>
	<segmented>0</segmented>
	<object>
		<name>LOUIS-VUITTON</name>
		<pose>Unspecified</pose>
		<truncated>0</truncated>
		<difficult>0</difficult>
		<bndbox>
			<xmin>66</xmin>
			<ymin>37</ymin>
			<xmax>293</xmax>
			<ymax>290</ymax>
		</bndbox>
	</object>
	<object>
		<name>LOUIS-VUITTON</name>
		<pose>Unspecified</pose>
		<truncated>0</truncated>
		<difficult>0</difficult>
		<bndbox>
			<xmin>10</xmin>
			<ymin>315</ymin>
			<xmax>381</xmax>
			<ymax>373</ymax>
		</bndbox>
	</object>
</annotation>